smart_injector/__init__.py
smart_injector/lifetime.py
smart_injector/types.py
smart_injector/utility.py
smart_injector/config/__init__.py
smart_injector/config/backend.py
smart_injector/config/user.py
smart_injector/container/__init__.py
smart_injector/container/container.py
smart_injector/container/factory.py
smart_injector/resolver/__init__.py
smart_injector/resolver/handlers.py
smart_injector/resolver/resolver.py
smart_injector-0.0.6.dist-info/AUTHORS.rst
smart_injector-0.0.6.dist-info/LICENSE
smart_injector-0.0.6.dist-info/METADATA
smart_injector-0.0.6.dist-info/WHEEL
smart_injector-0.0.6.dist-info/top_level.txt
smart_injector-0.0.6.dist-info/RECORD
