Metadata-Version: 2.1
Name: smart-injector
Version: 0.0.6
Summary: An easy to use lightweight dependency injection framework
Home-page: https://github.com/hlevering/python-smart-injector
Author: Hendrik Levering
Author-email: h.levering.git@gmail.com
License: BSD-2-Clause
Project-URL: Documentation, https://python-smart-injector.readthedocs.io/
Project-URL: Changelog, https://python-smart-injector.readthedocs.io/en/latest/changelog.html
Project-URL: Issue Tracker, https://github.com/hlevering/python-smart-injector/issues
Platform: UNKNOWN
Classifier: Development Status :: 5 - Production/Stable
Classifier: Intended Audience :: Developers
Classifier: License :: OSI Approved :: BSD License
Classifier: Operating System :: Unix
Classifier: Operating System :: POSIX
Classifier: Operating System :: Microsoft :: Windows
Classifier: Programming Language :: Python
Classifier: Programming Language :: Python :: 3
Classifier: Programming Language :: Python :: 3.5
Classifier: Programming Language :: Python :: 3.6
Classifier: Programming Language :: Python :: 3.7
Classifier: Programming Language :: Python :: 3.8
Classifier: Programming Language :: Python :: Implementation :: CPython
Classifier: Topic :: Utilities
Requires-Python: >=3.5
